{
  "type": "create:sequenced_assembly",
  "ingredient": {
    "item": "create_klinks_n_klangs:unpainted_ultra_ball"
  },
  "transitionalItem": {
    "item": "create_klinks_n_klangs:unfinished_ultra_ball"
  },
  "sequence": [
    {
      "type": "create:filling",
      "ingredients": [
        {
          "item": "create_klinks_n_klangs:unfinished_ultra_ball"
        },
        {
          "amount": 250,
          "fluid": "create_klinks_n_klangs:yellow_paint",
          "nbt": {}
        }
      ],
      "results": [
        {
          "item": "create_klinks_n_klangs:unfinished_ultra_ball"
        }
      ]
    },
    {
      "type": "create:filling",
      "ingredients": [
        {
          "item": "create_klinks_n_klangs:unfinished_ultra_ball"
        },
        {
          "amount": 250,
          "fluid": "create_klinks_n_klangs:black_paint",
          "nbt": {}
        }
      ],
      "results": [
        {
          "item": "create_klinks_n_klangs:unfinished_ultra_ball"
        }
      ]
    },
    {
      "type": "create:filling",
      "ingredients": [
        {
          "item": "create_klinks_n_klangs:unfinished_ultra_ball"
        },
        {
          "amount": 250,
          "fluid": "create_klinks_n_klangs:yellow_paint",
          "nbt": {}
        }
      ],
      "results": [
        {
          "item": "create_klinks_n_klangs:unfinished_ultra_ball"
        }
      ]
    },
    {
      "type": "create:deploying",
      "ingredients": [
        {
          "item": "create_klinks_n_klangs:unfinished_ultra_ball"
        },
        {
          "item": "society:fire_quartz"
        }
      ],
      "results": [
        {
          "item": "create_klinks_n_klangs:unfinished_ultra_ball"
        }
      ]
    }
  ],
  "results": [
    {
      "item": "cobblemon:ultra_ball"
    }
  ],
  "loops": 1
}
