{
	"shop_id": "bs_greenhouse",
	"name": "shop.society_trading.building_shop.greenhouse",
	"texture": "dialog:textures/portraits/carpenter",
	"hidden_from_selector": true,
	"display_type": "image",
	"jei_catalyst": {
		"item": "moreminecarts:chiseled_organic_glass"
	},
	"trades": [
		{
			"offer": {
				"item": "portable_blueprints:worn_blueprint",
				"nbt": "{Damage:1,allow_nbt:1,altezza:0,blueprint_name:\"greenhouse_basic\",buildAnyway:0b,display:{Name:'{\"italic\":false,\"color\":\"#FFFF00\",\"translate\":\"portable_blueprints.worn_blueprint.basic_greenhouse\"}',Lore:['{\"italic\":false,\"color\":\"#FFFF00\",\"translate\":\"portable_blueprints.worn_blueprint.basic_greenhouse.author\"}']},free_build:1,inventari_blocco_selezionati:\"\",lunghezzaX:0,lunghezzaZ:0,mirrowX:0b,mirrowY:0b,mirrowZ:0b,nome:\"greenhouse_basic\",owner:\"worn\",owner_name:Ace,remaining_uses:1,rotateValue:0s,skipObstructionBlock:0b,visualizeBuild:1b,wasHolding:1b,worn_set:1b}",
				"count": 1
			},
			"request": {
				"item": "meadow:fire_log",
				"count": 32
			},
			"image": "society:textures/gui/buildings/basic/greenhouse_basic",
			"image_description": "portable_blueprints.worn_blueprint.basic_greenhouse.dimensions",
			"trade_id": "bs_greenhouse_basic"
		},
		{
			"offer": {
				"item": "portable_blueprints:worn_blueprint",
				"nbt": "{Damage:1,allow_nbt:1,altezza:0,blueprint_name:\"greenhouse_alpine\",buildAnyway:0b,display:{Name:'{\"italic\":false,\"color\":\"#FFFF00\",\"translate\":\"portable_blueprints.worn_blueprint.alpine_greenhouse\"}',Lore:['{\"italic\":false,\"color\":\"#FFFF00\",\"translate\":\"portable_blueprints.worn_blueprint.alpine_greenhouse.author\"}']},free_build:1,inventari_blocco_selezionati:\"\",lunghezzaX:0,lunghezzaZ:0,mirrowX:0b,mirrowY:0b,mirrowZ:0b,nome:\"greenhouse_alpine\",owner:\"worn\",owner_name:Ace,remaining_uses:1,rotateValue:0s,skipObstructionBlock:0b,visualizeBuild:1b,wasHolding:1b,worn_set:1b}",
				"count": 1
			},
			"request": {
				"item": "meadow:fire_log",
				"count": 32
			},
			"image": "society:textures/gui/buildings/alpine/greenhouse_alpine",
			"image_description": "portable_blueprints.worn_blueprint.alpine_greenhouse.dimensions",
			"trade_id": "bs_greenhouse_alpine"
		},
		{
			"offer": {
				"item": "portable_blueprints:worn_blueprint",
				"nbt": "{Damage:1,allow_nbt:1,altezza:0,blueprint_name:\"greenhouse_arid\",buildAnyway:0b,display:{Name:'{\"italic\":false,\"color\":\"#FFFF00\",\"translate\":\"portable_blueprints.worn_blueprint.arid_greenhouse\"}',Lore:['{\"italic\":false,\"color\":\"#FFFF00\",\"translate\":\"portable_blueprints.worn_blueprint.arid_greenhouse.author\"}']},free_build:1,inventari_blocco_selezionati:\"\",lunghezzaX:0,lunghezzaZ:0,mirrowX:0b,mirrowY:0b,mirrowZ:0b,nome:\"greenhouse_arid\",owner:\"worn\",owner_name:Ace,remaining_uses:1,rotateValue:0s,skipObstructionBlock:0b,visualizeBuild:1b,wasHolding:1b,worn_set:1b}",
				"count": 1
			},
			"request": {
				"item": "meadow:fire_log",
				"count": 32
			},
			"image": "society:textures/gui/buildings/arid/greenhouse_arid",
			"image_description": "portable_blueprints.worn_blueprint.arid_greenhouse.dimensions",
			"trade_id": "bs_greenhouse_arid"
		},
		{
			"offer": {
				"item": "portable_blueprints:worn_blueprint",
				"nbt": "{Damage:1,allow_nbt:1,altezza:0,blueprint_name:\"greenhouse_bamboo\",buildAnyway:0b,display:{Name:'{\"italic\":false,\"color\":\"#FFFF00\",\"translate\":\"portable_blueprints.worn_blueprint.bamboo_greenhouse\"}',Lore:['{\"italic\":false,\"color\":\"#FFFF00\",\"translate\":\"portable_blueprints.worn_blueprint.bamboo_greenhouse.author\"}']},free_build:1,inventari_blocco_selezionati:\"\",lunghezzaX:0,lunghezzaZ:0,mirrowX:0b,mirrowY:0b,mirrowZ:0b,nome:\"greenhouse_bamboo\",owner:\"worn\",owner_name:Ace,remaining_uses:1,rotateValue:0s,skipObstructionBlock:0b,visualizeBuild:1b,wasHolding:1b,worn_set:1b}",
				"count": 1
			},
			"request": {
				"item": "meadow:fire_log",
				"count": 32
			},
			"image": "society:textures/gui/buildings/bamboo/greenhouse_bamboo",
			"image_description": "portable_blueprints.worn_blueprint.bamboo_greenhouse.dimensions",
			"trade_id": "bs_greenhouse_bamboo"
		},
		{
			"offer": {
				"item": "portable_blueprints:worn_blueprint",
				"nbt": "{Damage:1,allow_nbt:1,altezza:0,blueprint_name:\"greenhouse_bavarian\",buildAnyway:0b,display:{Name:'{\"italic\":false,\"color\":\"#FFFF00\",\"translate\":\"portable_blueprints.worn_blueprint.bavarian_greenhouse\"}',Lore:['{\"italic\":false,\"color\":\"#FFFF00\",\"translate\":\"portable_blueprints.worn_blueprint.bavarian_greenhouse.author\"}']},free_build:1,inventari_blocco_selezionati:\"\",lunghezzaX:0,lunghezzaZ:0,mirrowX:0b,mirrowY:0b,mirrowZ:0b,nome:\"greenhouse_bavarian\",owner:\"worn\",owner_name:Ace,remaining_uses:1,rotateValue:0s,skipObstructionBlock:0b,visualizeBuild:1b,wasHolding:1b,worn_set:1b}",
				"count": 1
			},
			"request": {
				"item": "meadow:fire_log",
				"count": 32
			},
			"image": "society:textures/gui/buildings/bavarian/greenhouse_bavarian",
			"image_description": "portable_blueprints.worn_blueprint.bavarian_greenhouse.dimensions",
			"trade_id": "bs_greenhouse_bavarian"
		},
		{
			"offer": {
				"item": "portable_blueprints:worn_blueprint",
				"nbt": "{Damage:1,allow_nbt:1,altezza:0,blueprint_name:\"greenhouse_cherry\",buildAnyway:0b,display:{Name:'{\"italic\":false,\"color\":\"#FFFF00\",\"translate\":\"portable_blueprints.worn_blueprint.cherry_greenhouse\"}',Lore:['{\"italic\":false,\"color\":\"#FFFF00\",\"translate\":\"portable_blueprints.worn_blueprint.cherry_greenhouse.author\"}']},free_build:1,inventari_blocco_selezionati:\"\",lunghezzaX:0,lunghezzaZ:0,mirrowX:0b,mirrowY:0b,mirrowZ:0b,nome:\"greenhouse_cherry\",owner:\"worn\",owner_name:Ace,remaining_uses:1,rotateValue:0s,skipObstructionBlock:0b,visualizeBuild:1b,wasHolding:1b,worn_set:1b}",
				"count": 1
			},
			"request": {
				"item": "meadow:fire_log",
				"count": 32
			},
			"image": "society:textures/gui/buildings/cherry/greenhouse_cherry",
			"image_description": "portable_blueprints.worn_blueprint.cherry_greenhouse.dimensions",
			"trade_id": "bs_greenhouse_cherry"
		},
		{
			"offer": {
				"item": "portable_blueprints:worn_blueprint",
				"nbt": "{Damage:1,allow_nbt:1,altezza:0,blueprint_name:\"greenhouse_entrana\",buildAnyway:0b,display:{Name:'{\"italic\":false,\"color\":\"#FFFF00\",\"translate\":\"portable_blueprints.worn_blueprint.entrana_greenhouse\"}',Lore:['{\"italic\":false,\"color\":\"#FFFF00\",\"translate\":\"portable_blueprints.worn_blueprint.entrana_greenhouse.author\"}']},free_build:1,inventari_blocco_selezionati:\"\",lunghezzaX:0,lunghezzaZ:0,mirrowX:0b,mirrowY:0b,mirrowZ:0b,nome:\"greenhouse_entrana\",owner:\"worn\",owner_name:Ace,remaining_uses:1,rotateValue:0s,skipObstructionBlock:0b,visualizeBuild:1b,wasHolding:1b,worn_set:1b}",
				"count": 1
			},
			"request": {
				"item": "meadow:fire_log",
				"count": 32
			},
			"image": "society:textures/gui/buildings/entrana/greenhouse_entrana",
			"image_description": "portable_blueprints.worn_blueprint.entrana_greenhouse.dimensions",
			"trade_id": "bs_greenhouse_entrana"
		},
		{
			"offer": {
				"item": "portable_blueprints:worn_blueprint",
				"nbt": "{Damage:1,allow_nbt:1,altezza:0,blueprint_name:\"greenhouse_mason\",buildAnyway:0b,display:{Name:'{\"italic\":false,\"color\":\"#FFFF00\",\"translate\":\"portable_blueprints.worn_blueprint.mason_greenhouse\"}',Lore:['{\"italic\":false,\"color\":\"#FFFF00\",\"translate\":\"portable_blueprints.worn_blueprint.mason_greenhouse.author\"}']},free_build:1,inventari_blocco_selezionati:\"\",lunghezzaX:0,lunghezzaZ:0,mirrowX:0b,mirrowY:0b,mirrowZ:0b,nome:\"greenhouse_mason\",owner:\"worn\",owner_name:Ace,remaining_uses:1,rotateValue:0s,skipObstructionBlock:0b,visualizeBuild:1b,wasHolding:1b,worn_set:1b}",
				"count": 1
			},
			"request": {
				"item": "meadow:fire_log",
				"count": 32
			},
			"image": "society:textures/gui/buildings/mason/greenhouse_mason",
			"image_description": "portable_blueprints.worn_blueprint.mason_greenhouse.dimensions",
			"trade_id": "bs_greenhouse_mason"
		},
		{
			"offer": {
				"item": "portable_blueprints:worn_blueprint",
				"nbt": "{Damage:1,allow_nbt:1,altezza:0,blueprint_name:\"greenhouse_prismarine\",buildAnyway:0b,display:{Name:'{\"italic\":false,\"color\":\"#FFFF00\",\"translate\":\"portable_blueprints.worn_blueprint.prismarine_greenhouse\"}',Lore:['{\"italic\":false,\"color\":\"#FFFF00\",\"translate\":\"portable_blueprints.worn_blueprint.prismarine_greenhouse.author\"}']},free_build:1,inventari_blocco_selezionati:\"\",lunghezzaX:0,lunghezzaZ:0,mirrowX:0b,mirrowY:0b,mirrowZ:0b,nome:\"greenhouse_prismarine\",owner:\"worn\",owner_name:Ace,remaining_uses:1,rotateValue:0s,skipObstructionBlock:0b,visualizeBuild:1b,wasHolding:1b,worn_set:1b}",
				"count": 1
			},
			"request": {
				"item": "meadow:fire_log",
				"count": 32
			},
			"image": "society:textures/gui/buildings/prismarine/greenhouse_prismarine",
			"image_description": "portable_blueprints.worn_blueprint.prismarine_greenhouse.dimensions",
			"trade_id": "bs_greenhouse_prismarine"
		},
		{
			"offer": {
				"item": "portable_blueprints:worn_blueprint",
				"nbt": "{Damage:1,allow_nbt:1,altezza:0,blueprint_name:\"greenhouse_siberian\",buildAnyway:0b,display:{Name:'{\"italic\":false,\"color\":\"#FFFF00\",\"translate\":\"portable_blueprints.worn_blueprint.siberian_greenhouse\"}',Lore:['{\"italic\":false,\"color\":\"#FFFF00\",\"translate\":\"portable_blueprints.worn_blueprint.siberian_greenhouse.author\"}']},free_build:1,inventari_blocco_selezionati:\"\",lunghezzaX:0,lunghezzaZ:0,mirrowX:0b,mirrowY:0b,mirrowZ:0b,nome:\"greenhouse_siberian\",owner:\"worn\",owner_name:Ace,remaining_uses:1,rotateValue:0s,skipObstructionBlock:0b,visualizeBuild:1b,wasHolding:1b,worn_set:1b}",
				"count": 1
			},
			"request": {
				"item": "meadow:fire_log",
				"count": 32
			},
			"image": "society:textures/gui/buildings/siberian/greenhouse_siberian",
			"image_description": "portable_blueprints.worn_blueprint.siberian_greenhouse.dimensions",
			"trade_id": "bs_greenhouse_siberian"
		},
		{
			"offer": {
				"item": "portable_blueprints:worn_blueprint",
				"nbt": "{Damage:1,allow_nbt:1,altezza:0,blueprint_name:\"greenhouse_tudor\",buildAnyway:0b,display:{Name:'{\"italic\":false,\"color\":\"#FFFF00\",\"translate\":\"portable_blueprints.worn_blueprint.tudor_greenhouse\"}',Lore:['{\"italic\":false,\"color\":\"#FFFF00\",\"translate\":\"portable_blueprints.worn_blueprint.tudor_greenhouse.author\"}']},free_build:1,inventari_blocco_selezionati:\"\",lunghezzaX:0,lunghezzaZ:0,mirrowX:0b,mirrowY:0b,mirrowZ:0b,nome:\"greenhouse_tudor\",owner:\"worn\",owner_name:Ace,remaining_uses:1,rotateValue:0s,skipObstructionBlock:0b,visualizeBuild:1b,wasHolding:1b,worn_set:1b}",
				"count": 1
			},
			"request": {
				"item": "meadow:fire_log",
				"count": 32
			},
			"image": "society:textures/gui/buildings/tudor/greenhouse_tudor",
			"image_description": "portable_blueprints.worn_blueprint.tudor_greenhouse.dimensions",
			"trade_id": "bs_greenhouse_tudor"
		},
		{
			"offer": {
				"item": "portable_blueprints:worn_blueprint",
				"nbt": "{Damage:1,allow_nbt:1,altezza:0,blueprint_name:\"greenhouse_vibrantown\",buildAnyway:0b,display:{Name:'{\"italic\":false,\"color\":\"#FFFF00\",\"translate\":\"portable_blueprints.worn_blueprint.vibrantown_greenhouse\"}',Lore:['{\"italic\":false,\"color\":\"#FFFF00\",\"translate\":\"portable_blueprints.worn_blueprint.vibrantown_greenhouse.author\"}']},free_build:1,inventari_blocco_selezionati:\"\",lunghezzaX:0,lunghezzaZ:0,mirrowX:0b,mirrowY:0b,mirrowZ:0b,nome:\"greenhouse_vibrantown\",owner:\"worn\",owner_name:Ace,remaining_uses:1,rotateValue:0s,skipObstructionBlock:0b,visualizeBuild:1b,wasHolding:1b,worn_set:1b}",
				"count": 1
			},
			"request": {
				"item": "meadow:fire_log",
				"count": 32
			},
			"image": "society:textures/gui/buildings/vibrantown/greenhouse_vibrantown",
			"image_description": "portable_blueprints.worn_blueprint.vibrantown_greenhouse.dimensions",
			"trade_id": "bs_greenhouse_vibrantown"
		},
		{
			"offer": {
				"item": "portable_blueprints:worn_blueprint",
				"nbt": "{Damage:1,allow_nbt:1,altezza:0,blueprint_name:\"greenhouse_floral\",buildAnyway:0b,display:{Name:'{\"italic\":false,\"color\":\"#FFFF00\",\"translate\":\"portable_blueprints.worn_blueprint.floral_greenhouse\"}',Lore:['{\"italic\":false,\"color\":\"#FFFF00\",\"translate\":\"portable_blueprints.worn_blueprint.floral_greenhouse.author\"}']},free_build:1,inventari_blocco_selezionati:\"\",lunghezzaX:0,lunghezzaZ:0,mirrowX:0b,mirrowY:0b,mirrowZ:0b,nome:\"greenhouse_floral\",owner:\"worn\",owner_name:Ace,remaining_uses:1,rotateValue:0s,skipObstructionBlock:0b,visualizeBuild:1b,wasHolding:1b,worn_set:1b}",
				"count": 1
			},
			"request": {
				"item": "meadow:fire_log",
				"count": 32
			},
			"image": "society:textures/gui/buildings/floral/greenhouse_floral",
			"image_description": "portable_blueprints.worn_blueprint.floral_greenhouse.dimensions",
			"trade_id": "bs_greenhouse_floral"
		},
		{
			"offer": {
				"item": "portable_blueprints:worn_blueprint",
				"nbt": "{Damage:1,allow_nbt:1,altezza:0,blueprint_name:\"greenhouse_sakura\",buildAnyway:0b,display:{Name:'{\"italic\":false,\"color\":\"#FFFF00\",\"translate\":\"portable_blueprints.worn_blueprint.sakura_greenhouse\"}',Lore:['{\"italic\":false,\"color\":\"#FFFF00\",\"translate\":\"portable_blueprints.worn_blueprint.sakura_greenhouse.author\"}']},free_build:1,inventari_blocco_selezionati:\"\",lunghezzaX:0,lunghezzaZ:0,mirrowX:0b,mirrowY:0b,mirrowZ:0b,nome:\"greenhouse_sakura\",owner:\"worn\",owner_name:Ace,remaining_uses:1,rotateValue:0s,skipObstructionBlock:0b,visualizeBuild:1b,wasHolding:1b,worn_set:1b}",
				"count": 1
			},
			"request": {
				"item": "meadow:fire_log",
				"count": 32
			},
			"image": "society:textures/gui/buildings/sakura/greenhouse_sakura",
			"image_description": "portable_blueprints.worn_blueprint.sakura_greenhouse.dimensions",
			"trade_id": "bs_greenhouse_sakura"
		}
	]
}